agnes/__init__.py
agnes/algos/__init__.py
agnes/algos/a2c.py
agnes/algos/base.py
agnes/algos/ppo.py
agnes/algos/ppo_rnd.py
agnes/algos/configs/__init__.py
agnes/algos/configs/a2c_config.py
agnes/algos/configs/ppo_config.py
agnes/common/__init__.py
agnes/common/distributions.py
agnes/common/env_maker.py
agnes/common/init_weights.py
agnes/common/logger.py
agnes/common/make_nn.py
agnes/common/play.py
agnes/common/plotter.py
agnes/common/rnd_networks.py
agnes/common/running_mean_std.py
agnes/common/schedules.py
agnes/common/envs_prep/__init__.py
agnes/common/envs_prep/atari_wrappers.py
agnes/common/envs_prep/dummy_vec_env.py
agnes/common/envs_prep/monitor.py
agnes/common/envs_prep/subproc_vec_env.py
agnes/common/envs_prep/tile_images.py
agnes/common/envs_prep/util.py
agnes/common/envs_prep/vec_env.py
agnes/common/envs_prep/vec_frame_stack.py
agnes/common/envs_prep/vec_normalize.py
agnes/common/envs_prep/wrappers.py
agnes/common/tests/CNN_Discrete.py
agnes/common/tests/MLP_Continuous.py
agnes/common/tests/MLP_Discrete.py
agnes/common/tests/MPI_MLP_Discrete.py
agnes/common/tests/MPI_runner.py
agnes/common/tests/RNN_Discrete.py
agnes/common/tests/__init__.py
agnes/nns/__init__.py
agnes/nns/base.py
agnes/nns/cnn.py
agnes/nns/initializer.py
agnes/nns/mlp.py
agnes/nns/rnn.py
agnes/runners/__init__.py
agnes/runners/base_runner.py
agnes/runners/distributed_mpi.py
agnes/runners/single.py
agnes-0.0.7.4.dist-info/LICENSE
agnes-0.0.7.4.dist-info/METADATA
agnes-0.0.7.4.dist-info/WHEEL
agnes-0.0.7.4.dist-info/top_level.txt
agnes-0.0.7.4.dist-info/RECORD
