Metadata-Version: 2.1
Name: agnes
Version: 0.0.7.4
Summary: AGNES - Flexible Reinforcement Learning Framework with PyTorch
Home-page: https://github.com/rotinov/AGNES
Author: Rotinov Egor
Author-email: rotinov-github@pm.me
License: MIT LICENSE
Keywords: PyTorch reinforcement learning ppo a2c framework random network distillation
Platform: UNKNOWN
Classifier: Programming Language :: Python :: 3
Classifier: License :: OSI Approved :: MIT License
Classifier: Intended Audience :: Science/Research
Classifier: Natural Language :: English
Classifier: Topic :: Scientific/Engineering :: Artificial Intelligence
Classifier: Operating System :: OS Independent
Requires-Dist: cloudpickle
Requires-Dist: gym[atari]
Requires-Dist: psutil
Requires-Dist: atari-py
Requires-Dist: numpy
Requires-Dist: torch (>=1.2)
Requires-Dist: opencv-python
Provides-Extra: all
Requires-Dist: mpi4py ; extra == 'all'
Requires-Dist: Tensorboard ; extra == 'all'
Provides-Extra: distributed
Requires-Dist: mpi4py ; extra == 'distributed'
Provides-Extra: tensorboard
Requires-Dist: Tensorboard ; extra == 'tensorboard'
